jupyter_tempvars/__init__.py
jupyter_tempvars/__main__.py
jupyter_tempvars/cli.py
jupyter_tempvars/version.py
jupyter_tempvars/extension/jupyter_tempvars.js
jupyter_tempvars/extension/jupyter_tempvars.yml
jupyter_tempvars-0.1.post1.dist-info/LICENSE.txt
jupyter_tempvars-0.1.post1.dist-info/METADATA
jupyter_tempvars-0.1.post1.dist-info/WHEEL
jupyter_tempvars-0.1.post1.dist-info/entry_points.txt
jupyter_tempvars-0.1.post1.dist-info/top_level.txt
jupyter_tempvars-0.1.post1.dist-info/RECORD
