Metadata-Version: 2.1
Name: jupyter-tempvars
Version: 0.1.post1
Summary: Jupyter Notebook extension providing per-cell temporary variables
Home-page: https://github.com/bskinn/jupyter-tempvars
Author-email: Brian Skinn <brian.skinn@gmail.com>
License: MIT License
Project-URL: Changelog, https://github.com/bskinn/jupyter-tempvars/blob/main/CHANGELOG.md
Project-URL: Docs, https://jupyter-tempvars.readthedocs.io/en/stable/
Project-URL: Donate, https://github.com/sponsors/bskinn
Project-URL: Homepage, https://github.com/bskinn/jupyter-tempvars
Project-URL: Thank, https://twitter.com/btskinn
Keywords: extension,jupyter,notebook,temporary variables
Platform: any
Classifier: License :: OSI Approved
Classifier: License :: OSI Approved :: MIT License
Classifier: Natural Language :: English
Classifier: Framework :: Jupyter
Classifier: Intended Audience :: Science/Research
Classifier: Operating System :: OS Independent
Classifier: Programming Language :: Python
Classifier: Programming Language :: Python :: 3
Classifier: Programming Language :: Python :: 3 :: Only
Classifier: Programming Language :: Python :: 3.7
Classifier: Programming Language :: Python :: 3.8
Classifier: Programming Language :: Python :: 3.9
Classifier: Programming Language :: Python :: 3.10
Classifier: Programming Language :: Python :: 3.11
Classifier: Topic :: Scientific/Engineering
Classifier: Development Status :: 4 - Beta
Requires-Python: >=3.7
License-File: LICENSE.txt
Requires-Dist: tempvars
